lunaengine/__init__.py
lunaengine/backend/__init__.py
lunaengine/backend/network.py
lunaengine/backend/openal.py
lunaengine/backend/opengl.py
lunaengine/backend/types.py
lunaengine/core/__init__.py
lunaengine/core/audio.py
lunaengine/core/engine.py
lunaengine/core/renderer.py
lunaengine/core/scene.py
lunaengine/core/window.py
lunaengine/graphics/__init__.py
lunaengine/graphics/camera.py
lunaengine/graphics/particles.py
lunaengine/graphics/shadows.py
lunaengine/graphics/spritesheet.py
lunaengine/misc/__init__.py
lunaengine/misc/bones.py
lunaengine/misc/icons.py
lunaengine/tools/__init__.py
lunaengine/tools/code_stats.py
lunaengine/tools/image_conversion_tool.py
lunaengine/ui/__init__.py
lunaengine/ui/elements.py
lunaengine/ui/layer_manager.py
lunaengine/ui/layout.py
lunaengine/ui/notifications.py
lunaengine/ui/styles.py
lunaengine/ui/themes.py
lunaengine/ui/tooltips.py
lunaengine/ui/tween.py
lunaengine/utils/__init__.py
lunaengine/utils/image_converter.py
lunaengine/utils/math_utils.py
lunaengine/utils/performance.py
lunaengine/utils/threading.py
lunaengine/utils/timer.py
lunaengine-0.2.0.dist-info/licenses/LICENSE
lunaengine-0.2.0.dist-info/METADATA
lunaengine-0.2.0.dist-info/WHEEL
lunaengine-0.2.0.dist-info/top_level.txt
lunaengine-0.2.0.dist-info/RECORD
