Metadata-Version: 2.4
Name: lunaengine
Version: 0.2.0
Summary: A modern 2D game engine with advanced UI and graphics
Home-page: https://github.com/MrJuaumBR/lunaengine
Author: MrJuaum
License: MIT
Project-URL: Homepage, https://mrjuaumbr.github.io/lunaengine/
Project-URL: Repository, https://github.com/MrJuaumBR/lunaengine
Project-URL: Issue Tracker, https://github.com/MrJuaumBR/lunaengine/issues
Keywords: game,engine,2d,graphics,pygame
Classifier: Development Status :: 3 - Alpha
Classifier: Intended Audience :: Developers
Classifier: License :: OSI Approved :: MIT License
Classifier: Programming Language :: Python :: 3
Classifier: Programming Language :: Python :: 3.8
Classifier: Programming Language :: Python :: 3.9
Classifier: Programming Language :: Python :: 3.10
Classifier: Programming Language :: Python :: 3.11
Requires-Python: >=3.9
License-File: LICENSE
Requires-Dist: pygame>=2.5.0
Requires-Dist: numpy>=1.21.0
Requires-Dist: PyOpenGL>=3.1.0
Requires-Dist: PyOpenGL-accelerate>=3.1.0
Requires-Dist: PyOpenAL
Requires-Dist: psutil
Provides-Extra: dev
Requires-Dist: black>=22.0.0; extra == "dev"
Requires-Dist: flake8>=4.0.0; extra == "dev"
Requires-Dist: pytest>=7.0.0; extra == "dev"
Requires-Dist: setuptools>=65.0.0; extra == "dev"
Requires-Dist: wheel>=0.37.0; extra == "dev"
Requires-Dist: twine>=4.0.0; extra == "dev"
Requires-Dist: build>=0.10.0; extra == "dev"
Dynamic: home-page
Dynamic: license-file
Dynamic: requires-python
